vag/__init__.py
vag/console/__init__.py
vag/console/application.py
vag/console/commands/__init__.py
vag/console/commands/cx.py
vag/console/commands/docker.py
vag/console/commands/gitea.py
vag/console/commands/remote.py
vag/console/commands/vagrant.py
vag/scripts/build/box.sh
vag/scripts/go.sh
vag/scripts/instance/list.sh
vag/scripts/nomad.sh
vag/utils/.gitignore
vag/utils/__init__.py
vag/utils/config.py
vag/utils/crypto_util.py
vag/utils/cx_db_util.py
vag/utils/cx_schema.py
vag/utils/cx_test_data.py
vag/utils/exec.py
vag/utils/gitea_api_util.py
vag/utils/hash_util.py
vag/utils/jenkins_util.py
vag/utils/misc.py
vag/utils/nomadutil.py
vag/utils/string_util.py
vag/utils/user_util.py
vag-0.1.55.dist-info/entry_points.txt
vag-0.1.55.dist-info/LICENSE
vag-0.1.55.dist-info/WHEEL
vag-0.1.55.dist-info/METADATA
vag-0.1.55.dist-info/RECORD
